DataDriver/AbstractReaderClass.py
DataDriver/DataDriver.py
DataDriver/ReaderConfig.py
DataDriver/__init__.py
DataDriver/argument_utils.py
DataDriver/csv_reader.py
DataDriver/generic_csv_reader.py
DataDriver/glob_reader.py
DataDriver/json_reader.py
DataDriver/pict_reader.py
DataDriver/rerunfailed.py
DataDriver/search.py
DataDriver/utils.py
DataDriver/xls_reader.py
DataDriver/xlsx_reader.py
robotframework_datadriver-1.11.2.dist-info/LICENSE
robotframework_datadriver-1.11.2.dist-info/METADATA
robotframework_datadriver-1.11.2.dist-info/WHEEL
robotframework_datadriver-1.11.2.dist-info/top_level.txt
robotframework_datadriver-1.11.2.dist-info/RECORD
