Metadata-Version: 2.1
Name: robotframework-datadriver
Version: 1.11.2
Summary: A library for Data-Driven Testing.
Home-page: https://github.com/Snooz82/robotframework-datadriver
Author: René Rohner(Snooz82)
Author-email: snooz@posteo.de
Classifier: Programming Language :: Python :: 3
Classifier: Programming Language :: Python :: 3.8
Classifier: Programming Language :: Python :: 3.9
Classifier: Programming Language :: Python :: 3.10
Classifier: Programming Language :: Python :: 3.11
Classifier: License :: OSI Approved :: Apache Software License
Classifier: Operating System :: OS Independent
Classifier: Topic :: Software Development :: Testing
Classifier: Topic :: Software Development :: Testing :: Acceptance
Classifier: Framework :: Robot Framework
Requires-Python: >=3.8.0
License-File: LICENSE
Requires-Dist: robotframework<8.0,>=4.0.2
Requires-Dist: docutils
Requires-Dist: Pygments
Provides-Extra: xls
Requires-Dist: pandas; extra == "xls"
Requires-Dist: xlrd>=1.2.0; extra == "xls"
Requires-Dist: openpyxl; extra == "xls"
